{
    "name": "ai.cerb.automationBuilder.input.text",
    "description": "",
    "extension_id": "cerb.trigger.interaction.internal",
    "script": "start:\r\n  await:\r\n    form:\r\n      elements:\r\n        say/type:\r\n          content: ## Inputs: Text\r\n  \r\n        text/prompt_key:\r\n          label: Key:\r\n          required@bool: yes\r\n          type: uri\r\n          placeholder: lowercase, a-z, 0-9, and underscore\r\n  \r\n        sheet/prompt_type:\r\n          label: Type:\r\n          data@json:\r\n            [\r\n              {\r\n                \"key\": \"freeform\",\r\n                \"name\": \"Freeform\",\r\n                \"description\": \"An arbitrary string of text\"\r\n              },\r\n              {\r\n                \"key\": \"bool\",\r\n                \"name\": \"Boolean\",\r\n                \"description\": \"true or false\"\r\n              },\r\n              {\r\n                \"key\": \"date\",\r\n                \"name\": \"Date\",\r\n                \"description\": \"tomorrow 5pm, +2 weeks, Friday\"\r\n              },\r\n              {\r\n                \"key\": \"decimal\",\r\n                \"name\": \"Decimal\",\r\n                \"description\": \"3.1415\"\r\n              },\r\n              {\r\n                \"key\": \"email\",\r\n                \"name\": \"Email\",\r\n                \"description\": \"client@example.com\"\r\n              },\r\n              {\r\n                \"key\": \"geopoint\",\r\n                \"name\": \"Geopoint\",\r\n                \"description\": \"44.226737, 20.7953 (lat, long)\"\r\n              },\r\n              {\r\n                \"key\": \"ip\",\r\n                \"name\": \"IP\",\r\n                \"description\": \"1.2.3.4 or a1b2:c3d4:e5f6:a1b2:c3d4:e5f6:a1b2:c3d4\"\r\n              },\r\n              {\r\n                \"key\": \"IPv4\",\r\n                \"name\": \"IPv4\",\r\n                \"description\": \"1.2.3.4\"\r\n              },\r\n              {\r\n                \"key\": \"IPv6\",\r\n                \"name\": \"IPv6\",\r\n                \"description\": \"a1b2:c3d4:e5f6:a1b2:c3d4:e5f6:a1b2:c3d4\"\r\n              },\r\n              {\r\n                \"key\": \"number\",\r\n                \"name\": \"Number\",\r\n                \"description\": \"1234\"\r\n              },\r\n              {\r\n                \"key\": \"record_type\",\r\n                \"name\": \"Record Type\",\r\n                \"description\": \"address, comment, ticket, worker\"\r\n              },\r\n              {\r\n                \"key\": \"timestamp\",\r\n                \"name\": \"Timestamp\",\r\n                \"description\": \"1601337600\"\r\n              },\r\n              {\r\n                \"key\": \"uri\",\r\n                \"name\": \"URI\",\r\n                \"description\": \"alphanumeric_with_underscores (a-z, 0-9, _)\"\r\n              },\r\n              {\r\n                \"key\": \"url\",\r\n                \"name\": \"URL\",\r\n                \"description\": \"https://example.com/path/file.png\"\r\n              }\r\n            ]\r\n          default@list:\r\n            freeform\r\n          schema:\r\n            layout:\r\n              headings@bool: no\r\n              paging@bool: no\r\n            columns:\r\n              selection/key:\r\n                params:\r\n                  mode: single\r\n              text/name:\r\n                params:\r\n                  bold@bool: yes\r\n              text/description:\r\n  \r\n        text/prompt_default:\r\n          label: Default:\r\n          type: freeform\r\n  \r\n        sheet/prompt_required:\r\n          label: Required:\r\n          required@bool: yes\r\n          data@json:\r\n            [\r\n              { \"name\": \"yes\" },\r\n              { \"name\": \"no\" }\r\n            ]\r\n          limit: 10\r\n          default: yes\r\n          schema:\r\n            layout:\r\n              headings@bool: no\r\n            columns:\r\n              selection/_selection:\r\n                params:\r\n                  mode: single\r\n                  value_key: name\r\n              text/name:\r\n\r\n  return:\r\n    snippet@text:\r\n      text/{{prompt_key|lower}}:\r\n        type: {{prompt_type}}\r\n        {% if prompt_required == 'yes' -%}\r\n        required@bool: yes\r\n        {% endif -%}\r\n        {% if prompt_default -%}\r\n        default: {{prompt_default}}\r\n        {% endif -%}",
    "policy_kata": "",
    "created_at": 1600722810,
    "updated_at": 1603141032
}